{
  "swagger": "2.0",
  "info": {
    "title": "Birthday Greeting Sample",
    "description": "API document about getting greeting message for people on birthday!",
    "version": "1.0.0"
  },
  "host": "localhost:5050",
  "basePath": "/",
  "schemes": [
    "http"
  ],
  "paths": {
    "/api/v6/greeting/birthday": {
      "get": {
        "tags": [
          "Greetings"
        ],
        "description": "Get birthday greetings for users whose birthdays are on the current day. The response is in XML format and contains greetings within a root element.",
        "produces": [
          "application/xml"
        ],
        "responses": {
          "200": {
            "description": "An XML list of birthday greetings for users, or an empty root element if no users have a birthday.",
            "content": {
              "application/xml": {
                "schema": {
                  "type": "string",
                  "example": "<root><greeting><title>Subject: Happy Birthday!</title><content>Happy birthday, dear John!</content></greeting><greeting><title>Subject: Happy Birthday!</title><content>Happy birthday, dear Jane!</content></greeting></root>"
                }
              }
            }
          },
          "500": {
            "description": "Internal Server Error"
          }
        }
      }
    }
  }
}